sage_aata/AlgebraicCoding.py
sage_aata/AutoKeyCipher.py
sage_aata/BCH.py
sage_aata/CeasarCipher.py
sage_aata/ConjugacyClasses.py
sage_aata/Cosets.py
sage_aata/Euclid.py
sage_aata/FrequencyAnalysis.py
sage_aata/GroupRings.py
sage_aata/HillCipher.py
sage_aata/Knapsack.py
sage_aata/PolynomialCodes.py
sage_aata/RSAEncryption.py
sage_aata/RepeatedSquares.py
sage_aata/VigenereCipher.py
sage_aata/__init__.py
sage_aata-1.0.dist-info/LICENSE
sage_aata-1.0.dist-info/METADATA
sage_aata-1.0.dist-info/WHEEL
sage_aata-1.0.dist-info/top_level.txt
sage_aata-1.0.dist-info/RECORD
