Metadata-Version: 2.1
Name: sage-aata
Version: 1.0
Summary: Package to implement standard Abstract Algebra computations in SageMath.
Home-page: https://github.com/bradencarlson/sage-jupyter
Author: Braden Carlson
Author-email: bradenjcarlson@live.com
License: UNKNOWN
Project-URL: Bug Tracker, https://github.com/bradencarlson/sage-jupyter/issues
Platform: UNKNOWN
Classifier: Programming Language :: Other
Classifier: License :: OSI Approved :: MIT License
Classifier: Operating System :: OS Independent
Requires-Python: >=3.6
License-File: LICENSE
